apiaccessor/__init__.py
apiaccessor-0.0.1.4.dist-info/LICENSE
apiaccessor-0.0.1.4.dist-info/METADATA
apiaccessor-0.0.1.4.dist-info/WHEEL
apiaccessor-0.0.1.4.dist-info/top_level.txt
apiaccessor-0.0.1.4.dist-info/RECORD
